ukbb_common/__init__.py
ukbb_common/resources/__init__.py
ukbb_common/resources/generic.py
ukbb_common/resources/results.py
ukbb_common/utils/__init__.py
ukbb_common/utils/annotations.py
ukbb_common/utils/generic.py
ukbb_common/utils/genotype_loading.py
ukbb_common/utils/phenotype_loading.py
ukbb_common/utils/phenotype_munging.py
ukbb_common/utils/results_loading.py
ukbb_common/utils/saige_pipeline.py
ukbb_common-0.1.2.dist-info/LICENSE
ukbb_common-0.1.2.dist-info/METADATA
ukbb_common-0.1.2.dist-info/WHEEL
ukbb_common-0.1.2.dist-info/top_level.txt
ukbb_common-0.1.2.dist-info/RECORD
